[
    {
        "title": "Just a thing we had",
        "author": "CarlosDoesTheWorld",
        "url": "https://i.redd.it/bd2i77cbwuba1.png",
        "text": "",
        "created_utc": 1673635646,
        "upvote_ratio": 1.0
    },
    {
        "title": "It was so hard",
        "author": "CarlosDoesTheWorld",
        "url": "https://i.redd.it/p3hrzfhxsuba1.png",
        "text": "",
        "created_utc": 1673634467,
        "upvote_ratio": 1.0
    },
    {
        "title": "I watched a Homeless Man Masturbate",
        "author": "Wyatt1710",
        "url": "https://i.redd.it/de8qa2tdjvba1.jpg",
        "text": "",
        "created_utc": 1673625376,
        "upvote_ratio": 1.0
    },
    {
        "title": "Podcast français : les femmes",
        "author": "jpsoeee3",
        "url": "https://youtu.be/TSxNRVzI2b0",
        "text": "",
        "created_utc": 1673564472,
        "upvote_ratio": 1.0
    },
    {
        "title": "CM Punjab Takes Vote Of Condifence From Punjab Assembly || After Much Ado, Elahi Proves Majority",
        "author": "Ok-Method9478",
        "url": "https://politicalpointofviewpk.blogspot.com/2023/01/CM-Punjab-Takes-Vote-Of-Condifence-From-Punjab-Assembly--After-much-ado-Elahi-proves-majority.html",
        "text": "",
        "created_utc": 1673533474,
        "upvote_ratio": 1.0
    },
    {
        "title": "New phone, wanna be my son?",
        "author": "kevinisrael",
        "url": "https://i.redd.it/ttnagau27nba1.jpg",
        "text": "",
        "created_utc": 1673524339,
        "upvote_ratio": 1.0
    },
    {
        "title": "And the award goes to…",
        "author": "roastmasterbash",
        "url": "https://i.redd.it/8o7dtdnzyiba1.jpg",
        "text": "",
        "created_utc": 1673473192,
        "upvote_ratio": 1.0
    },
    {
        "title": "Charming Scene from the Songhua River in China || Ice flower on Songhua River in Northeast China",
        "author": "Ok-Method9478",
        "url": "https://politicalpointofviewpk.blogspot.com/2023/01/Ice-flower-on-Songhua-River-in-Northeast-China.html",
        "text": "",
        "created_utc": 1673420582,
        "upvote_ratio": 1.0
    },
    {
        "title": "Having an infant son alerts me to the fact that every man, at one point, has peed on his own face. — Olivia Wilde",
        "author": "ScottBolander-Funny",
        "url": "https://i.redd.it/yzrc699plcba1.jpg",
        "text": "",
        "created_utc": 1673414752,
        "upvote_ratio": 1.0
    },
    {
        "title": "Sometimes I Buy Fentanyl",
        "author": "Wyatt1710",
        "url": "https://i.redd.it/6tpea8ummaba1.jpg",
        "text": "",
        "created_utc": 1673372183,
        "upvote_ratio": 1.0
    },
    {
        "title": "Homo-Kitty? | by u/ReliableRoommate",
        "author": "Huncko",
        "url": "https://youtube.com/shorts/U_8hcvYxMh0?feature=share",
        "text": "",
        "created_utc": 1673371610,
        "upvote_ratio": 1.0
    },
    {
        "title": "Food Jokes!",
        "author": "Wyatt1710",
        "url": "https://i.redd.it/vkmipajbbaba1.jpg",
        "text": "",
        "created_utc": 1673368380,
        "upvote_ratio": 1.0
    },
    {
        "title": "Look for Listings With the Redfin App! Mobail apps you are apps install and 5$ dollar earn.",
        "author": "riktakhatun10",
        "url": "https://cutt.ly/v2IpRL8",
        "text": "",
        "created_utc": 1673364768,
        "upvote_ratio": 1.0
    },
    {
        "title": "haha check this out 🤣 if you like please smash like button!",
        "author": "methodicalfunny",
        "url": "https://m.youtube.com/watch?v=iK7VLlXQarM",
        "text": "",
        "created_utc": 1673356759,
        "upvote_ratio": 1.0
    },
    {
        "title": "Cats Vs. Kids",
        "author": "Marysantora",
        "url": "https://i.redd.it/kt3evvbe16ba1.jpg",
        "text": "",
        "created_utc": 1673316612,
        "upvote_ratio": 1.0
    },
    {
        "title": "T-Minus 10 'til Friday",
        "author": "LeviSalt",
        "url": "https://i.redd.it/zjmieehnu2ba1.png",
        "text": "",
        "created_utc": 1673296049,
        "upvote_ratio": 1.0
    },
    {
        "title": "Thatd be like hailstorms calling themselves \"free ice cube distribution.\"",
        "author": "Max_Rezna",
        "url": "https://i.redd.it/wkexvy14v1ba1.jpg",
        "text": "",
        "created_utc": 1673284447,
        "upvote_ratio": 1.0
    },
    {
        "title": "Wholesome Bukkake",
        "author": "Wyatt1710",
        "url": "https://i.redd.it/gf1a5ejv33ba1.jpg",
        "text": "",
        "created_utc": 1673281130,
        "upvote_ratio": 1.0
    },
    {
        "title": "Work of Crowd",
        "author": "halfvideo",
        "url": "https://i.redd.it/zuyuo2dt6yaa1.png",
        "text": "",
        "created_utc": 1673239581,
        "upvote_ratio": 1.0
    },
    {
        "title": "Patience is a Virtue",
        "author": "Both_Tone",
        "url": "https://i.redd.it/ajvwiebo4xaa1.jpg",
        "text": "",
        "created_utc": 1673226802,
        "upvote_ratio": 1.0
    },
    {
        "title": "Dogs versus Cats",
        "author": "halfvideo",
        "url": "https://i.redd.it/kfgqp1i4guaa1.png",
        "text": "",
        "created_utc": 1673194291,
        "upvote_ratio": 1.0
    },
    {
        "title": "Putting it into “Ice Cream Terms”",
        "author": "Wyatt1710",
        "url": "https://i.redd.it/4p7tzzvlxvaa1.jpg",
        "text": "",
        "created_utc": 1673194274,
        "upvote_ratio": 1.0
    },
    {
        "title": "https://youtu.be/t26BfZG_KI4",
        "author": "Safe_Exchange_8426",
        "url": "https://i.redd.it/l4p558xjruaa1.jpg",
        "text": "",
        "created_utc": 1673180127,
        "upvote_ratio": 1.0
    },
    {
        "title": "She gave me the old one-two! One to put me down, two to make sure I never get up again!",
        "author": "AdvaitKomedian",
        "url": "https://i.redd.it/nomtaskzkoaa1.jpg",
        "text": "",
        "created_utc": 1673123290,
        "upvote_ratio": 1.0
    },
    {
        "title": "I Cheated On My Girlfriend…",
        "author": "Wyatt1710",
        "url": "https://i.redd.it/0hbn9zo0roaa1.jpg",
        "text": "",
        "created_utc": 1673107308,
        "upvote_ratio": 1.0
    },
    {
        "title": "Put it into “Ice Cream Terms”",
        "author": "Wyatt1710",
        "url": "https://i.redd.it/0hipuy77joaa1.jpg",
        "text": "",
        "created_utc": 1673104677,
        "upvote_ratio": 1.0
    },
    {
        "title": "Use what you have to your advantage!",
        "author": "alexschubs",
        "url": "https://i.redd.it/xln23pkdbgaa1.png",
        "text": "",
        "created_utc": 1673023344,
        "upvote_ratio": 1.0
    },
    {
        "title": "#мемы0sergeyuqasa2",
        "author": "Forward_Message2933",
        "url": "https://youtube.com/shorts/79Cp7Ddf8jg?feature=share",
        "text": "",
        "created_utc": 1673015321,
        "upvote_ratio": 1.0
    },
    {
        "title": "The stakes have escalated",
        "author": "DwightSimmonsComedy",
        "url": "https://i.redd.it/dca72xxh9caa1.png",
        "text": "",
        "created_utc": 1672956132,
        "upvote_ratio": 1.0
    },
    {
        "title": "I Told My Girlfriend That I Only Watch Porn that Looks Like Her…",
        "author": "Wyatt1710",
        "url": "https://i.redd.it/abuylgu6xaaa1.jpg",
        "text": "",
        "created_utc": 1672939887,
        "upvote_ratio": 1.0
    },
    {
        "title": "The Best Food is from the Restaurants with the Worst Names!",
        "author": "Wyatt1710",
        "url": "https://i.redd.it/z0th1l2omaaa1.jpg",
        "text": "",
        "created_utc": 1672936359,
        "upvote_ratio": 1.0
    },
    {
        "title": "Gente de Reddit que carrera sería la mejor eligir electrónica o administración",
        "author": "Shot-Positive-4621",
        "url": "https://www.reddit.com/r/standupshots/comments/103ppnr/gente_de_reddit_que_carrera_sería_la_mejor_eligir/",
        "text": "",
        "created_utc": 1672893609,
        "upvote_ratio": 1.0
    },
    {
        "title": "Sobriety is my child",
        "author": "Marysantora",
        "url": "https://i.redd.it/76unddcgd5aa1.jpg",
        "text": "",
        "created_utc": 1672872711,
        "upvote_ratio": 1.0
    },
    {
        "title": "You'll win a brand new criminal record",
        "author": "Max_Rezna",
        "url": "https://i.redd.it/cxp2gm7ur3aa1.jpg",
        "text": "",
        "created_utc": 1672871413,
        "upvote_ratio": 1.0
    },
    {
        "title": "Just my family?",
        "author": "DwightSimmonsComedy",
        "url": "https://i.redd.it/qhfzub18s4aa1.png",
        "text": "",
        "created_utc": 1672865578,
        "upvote_ratio": 1.0
    },
    {
        "title": "What if Jesus was Aborted?",
        "author": "Wyatt1710",
        "url": "https://i.redd.it/qohamw2dj3aa1.jpg",
        "text": "",
        "created_utc": 1672850663,
        "upvote_ratio": 1.0
    },
    {
        "title": "a new joke that I have been working on",
        "author": "CreamComedy",
        "url": "https://i.redd.it/zbkugn9hby9a1.jpg",
        "text": "",
        "created_utc": 1672787299,
        "upvote_ratio": 1.0
    },
    {
        "title": "I am very poor !",
        "author": "Evening_Rough_8781",
        "url": "https://i.redd.it/xhit963dby9a1.jpg",
        "text": "",
        "created_utc": 1672787260,
        "upvote_ratio": 1.0
    },
    {
        "title": "“Jesus didn’t die from a Cruxifixion I don’t think he’ll die from a Coat Hanger”",
        "author": "Wyatt1710",
        "url": "https://i.redd.it/yuuc92ddrx9a1.jpg",
        "text": "",
        "created_utc": 1672780540,
        "upvote_ratio": 1.0
    },
    {
        "title": "What if Jesus was Aborted?",
        "author": "Wyatt1710",
        "url": "https://i.redd.it/wnn8t4709x9a1.jpg",
        "text": "",
        "created_utc": 1672774364,
        "upvote_ratio": 1.0
    },
    {
        "title": "What if Jesus Was Aborted?",
        "author": "Wyatt1710",
        "url": "https://i.redd.it/sqyu8mw90x9a1.jpg",
        "text": "",
        "created_utc": 1672771428,
        "upvote_ratio": 1.0
    },
    {
        "title": "привет.",
        "author": "kto_to123",
        "url": "https://www.reddit.com/r/standupshots/comments/102f49p/привет/",
        "text": "[removed]",
        "created_utc": 1672769806,
        "upvote_ratio": 1.0
    },
    {
        "title": "What if Jesus Was Aborted?",
        "author": "Wyatt1710",
        "url": "https://i.redd.it/a3r17s60hw9a1.jpg",
        "text": "",
        "created_utc": 1672764947,
        "upvote_ratio": 1.0
    },
    {
        "title": "The first boop on the nose is free, but then you gotta pay.",
        "author": "kevinisrael",
        "url": "https://i.redd.it/g8qmqh7n5v9a1.jpg",
        "text": "",
        "created_utc": 1672749016,
        "upvote_ratio": 1.0
    },
    {
        "title": "65ING | JordanQbaum",
        "author": "jordanqbaum",
        "url": "https://i.redd.it/bf6j6o8wot9a1.jpg",
        "text": "",
        "created_utc": 1672731277,
        "upvote_ratio": 1.0
    },
    {
        "title": "momos",
        "author": "fetuchiti",
        "url": "https://i.redd.it/iojf79ybzq9a1.jpg",
        "text": "",
        "created_utc": 1672698465,
        "upvote_ratio": 1.0
    },
    {
        "title": "Don’t Pass Out At A Gay Frat…",
        "author": "Wyatt1710",
        "url": "https://i.redd.it/ei8uhhc2fp9a1.jpg",
        "text": "Watch My Full Comedy Special:\n\nhttps://m.youtube.com/watch?v=5dYhA29lXl4",
        "created_utc": 1672679545,
        "upvote_ratio": 1.0
    },
    {
        "title": "I Passed Out At An All Gay Frat Party…",
        "author": "Wyatt1710",
        "url": "https://i.redd.it/9lvo1u1jap9a1.jpg",
        "text": "Watch My Full Special:\n\nhttps://m.youtube.com/watch?v=5dYhA29lXl4",
        "created_utc": 1672678019,
        "upvote_ratio": 1.0
    },
    {
        "title": "Chiggy the pig from 8rooklyn",
        "author": "8igchiggy",
        "url": "https://i.redd.it/1gyh3m7duk9a1.jpg",
        "text": "",
        "created_utc": 1672624154,
        "upvote_ratio": 1.0
    },
    {
        "title": "Is this herpes ?",
        "author": "Rude_Button_7661",
        "url": "https://i.redd.it/v2w2qu627j9a1.jpg",
        "text": "",
        "created_utc": 1672604210,
        "upvote_ratio": 1.0
    },
    {
        "title": "Six Years Ago, I got 25K Upvotes here for This Joke. Now First My Comedy Special Is Out!",
        "author": "Wyatt1710",
        "url": "https://i.redd.it/derqupop9i9a1.jpg",
        "text": "Here’s My Special:\n\nhttps://m.youtube.com/watch?v=5dYhA29lXl4",
        "created_utc": 1672592997,
        "upvote_ratio": 1.0
    },
    {
        "title": "Obama on Mount Rushmore",
        "author": "Wyatt1710",
        "url": "https://i.redd.it/b1seyuxs0i9a1.jpg",
        "text": "Hey everyone! Check out my Full Comedy Special:\n\nhttps://m.youtube.com/watch?v=5dYhA29lXl4",
        "created_utc": 1672590002,
        "upvote_ratio": 1.0
    },
    {
        "title": "Maybe that's where sock puppets come from... It's going to be a good year! The numbers don't lie!",
        "author": "AdvaitKomedian",
        "url": "https://i.redd.it/yw9p0aoxke9a1.jpg",
        "text": "",
        "created_utc": 1672566347,
        "upvote_ratio": 1.0
    },
    {
        "title": "Just changed which gods I pray to",
        "author": "Marysantora",
        "url": "https://i.redd.it/mma5653rec9a1.jpg",
        "text": "",
        "created_utc": 1672522048,
        "upvote_ratio": 1.0
    },
    {
        "title": "The work force is hard",
        "author": "CarlosDoesTheWorld",
        "url": "https://i.redd.it/ktawim3dub9a1.jpg",
        "text": "",
        "created_utc": 1672515191,
        "upvote_ratio": 1.0
    },
    {
        "title": "Jesus WAS White!",
        "author": "Wyatt1710",
        "url": "https://i.redd.it/drt483vwsa9a1.jpg",
        "text": "Watch my new Comedy Special! It would mean the world to me:\n\nhttps://m.youtube.com/watch?v=5dYhA29lXl4",
        "created_utc": 1672502602,
        "upvote_ratio": 1.0
    },
    {
        "title": "I Look Like What Jesus Really Looked Like…",
        "author": "Wyatt1710",
        "url": "https://i.redd.it/4lptsxd1oa9a1.jpg",
        "text": "Check Out my new Comedy Special! \n\nhttps://m.youtube.com/watch?v=5dYhA29lXl4",
        "created_utc": 1672500976,
        "upvote_ratio": 1.0
    },
    {
        "title": "You like Dark Humor? Watch my new Comedy Special!",
        "author": "Wyatt1710",
        "url": "https://i.redd.it/tutyt0mgha9a1.jpg",
        "text": "https://m.youtube.com/watch?v=5dYhA29lXl4",
        "created_utc": 1672498753,
        "upvote_ratio": 1.0
    },
    {
        "title": "White Trash Mortgage",
        "author": "Thhgtc",
        "url": "https://youtube.com/shorts/YomMfAVHTdo?feature=share",
        "text": "",
        "created_utc": 1672445976,
        "upvote_ratio": 1.0
    },
    {
        "title": "It's weird that I even had to write this joke",
        "author": "highogbabblebush",
        "url": "https://i.redd.it/gnk8z021f39a1.jpg",
        "text": "",
        "created_utc": 1672413179,
        "upvote_ratio": 1.0
    },
    {
        "title": "I started posting jokes on Reddit when I was 12. Yesterday my first Standup Special Released!",
        "author": "Wyatt1710",
        "url": "https://i.redd.it/5k24drejw29a1.jpg",
        "text": "",
        "created_utc": 1672406965,
        "upvote_ratio": 1.0
    },
    {
        "title": "“Christmas is a time when you get homesick, even if you’re home.” — Carol Nelson",
        "author": "ScottBolander-Funny",
        "url": "https://i.redd.it/ehtwc84lpr8a1.jpg",
        "text": "",
        "created_utc": 1672290714,
        "upvote_ratio": 1.0
    },
    {
        "title": "Egypt is WILD",
        "author": "highogbabblebush",
        "url": "https://i.redd.it/vu923btgtq8a1.jpg",
        "text": "",
        "created_utc": 1672260645,
        "upvote_ratio": 1.0
    },
    {
        "title": "I’m the butt of the joke.",
        "author": "gregtellsjokes",
        "url": "https://i.imgur.com/hBUdqk2.jpg",
        "text": "",
        "created_utc": 1672251919,
        "upvote_ratio": 1.0
    },
    {
        "title": "GAME ONLINE PENGHASIL UANG SLOT COBABET805 HADIR MENJAMIN KEGACORAN - BONUS PENGGUNA BARU 100% - GARANSI POLA PENGGUNA - BONUS UNTUK PENGGUNA LAMA 20% 👇👇👇👇 https://bit.ly/3I0Sh1q",
        "author": "COBABET805",
        "url": "https://i.redd.it/2dhs6vjjok8a1.jpg",
        "text": "",
        "created_utc": 1672204350,
        "upvote_ratio": 1.0
    },
    {
        "title": "how much did you pay for the shipping address",
        "author": "hiottvn",
        "url": "https://www.grocafrica.com/download?link=F8tiBeGpJSCH5Ez",
        "text": "",
        "created_utc": 1672203155,
        "upvote_ratio": 1.0
    },
    {
        "title": "GAME ONLINE PENGHASIL UANG SLOT COBABET805 HADIR MENJAMIN KEGACORAN - BONUS PENGGUNA BARU 100% - GARANSI POLA PENGGUNA - BONUS UNTUK PENGGUNA LAMA 20%",
        "author": "COBABET805",
        "url": "https://www.reddit.com/r/standupshots/comments/zx0jhb/game_online_penghasil_uang_slot_cobabet805_hadir/",
        "text": "[removed]",
        "created_utc": 1672202673,
        "upvote_ratio": 1.0
    },
    {
        "title": "I'm swamped with activism",
        "author": "IAmABouncer",
        "url": "https://i.redd.it/7uz03ve0bi8a1.png",
        "text": "",
        "created_utc": 1672176955,
        "upvote_ratio": 1.0
    },
    {
        "title": "Lessons from a gambler",
        "author": "Marysantora",
        "url": "https://i.redd.it/hdbemzxkdj8a1.jpg",
        "text": "",
        "created_utc": 1672170555,
        "upvote_ratio": 1.0
    },
    {
        "title": "I never brag to you about where I sleep in my 1BR",
        "author": "Max_Rezna",
        "url": "https://i.redd.it/sje22f712h8a1.jpg",
        "text": "",
        "created_utc": 1672160722,
        "upvote_ratio": 1.0
    },
    {
        "title": "Buen viejo Los Ángeles.",
        "author": "SignalNo98",
        "url": "https://i.redd.it/oyvhow8uy88a1.png",
        "text": "",
        "created_utc": 1672062536,
        "upvote_ratio": 1.0
    },
    {
        "title": "1 out of 10",
        "author": "deepIntrude284",
        "url": "https://i.redd.it/2ahm81zmd68a1.jpg",
        "text": "",
        "created_utc": 1672031197,
        "upvote_ratio": 1.0
    },
    {
        "title": "good😇im tilted guys",
        "author": "s1ndzy",
        "url": "https://i.redd.it/0cu9popxz68a1.jpg",
        "text": "",
        "created_utc": 1672020690,
        "upvote_ratio": 1.0
    },
    {
        "title": "2 hours of work = 1 bag of weed",
        "author": "CarlosDoesTheWorld",
        "url": "https://i.redd.it/wxxhpcuyr68a1.jpg",
        "text": "",
        "created_utc": 1672018003,
        "upvote_ratio": 1.0
    },
    {
        "title": "I am not above fart jokes",
        "author": "JZcomedy",
        "url": "https://i.redd.it/u88pkuvt2t7a1.jpg",
        "text": "",
        "created_utc": 1671852160,
        "upvote_ratio": 1.0
    },
    {
        "title": "You didn’t have to keep going 😭🤷🏻‍♂️",
        "author": "CarlosDoesTheWorld",
        "url": "https://i.redd.it/vttmjuxjcq7a1.jpg",
        "text": "",
        "created_utc": 1671819111,
        "upvote_ratio": 1.0
    },
    {
        "title": "https://share.getcashto.com/@queentiye513",
        "author": "QueenTiye513",
        "url": "https://www.reddit.com/r/standupshots/comments/ztmkyp/httpssharegetcashtocomqueentiye513/",
        "text": "",
        "created_utc": 1671815243,
        "upvote_ratio": 1.0
    },
    {
        "title": "It's not lying, it's just telling a better truth",
        "author": "IAmABouncer",
        "url": "https://i.redd.it/qysj8k9l3i7a1.png",
        "text": "",
        "created_utc": 1671737275,
        "upvote_ratio": 1.0
    },
    {
        "title": "PSA on cigarettes",
        "author": "POOPSCRUFFIN4U",
        "url": "https://i.redd.it/ibir5vn74h7a1.jpg",
        "text": "",
        "created_utc": 1671725373,
        "upvote_ratio": 1.0
    },
    {
        "title": "Anything to help the kids",
        "author": "Frankfusion",
        "url": "https://i.redd.it/2fxyl3v42c7a1.jpg",
        "text": "",
        "created_utc": 1671664125,
        "upvote_ratio": 1.0
    },
    {
        "title": "Anything to help the kids",
        "author": "Frankfusion",
        "url": "https://imgflip.com/i/754pfz",
        "text": "",
        "created_utc": 1671664033,
        "upvote_ratio": 1.0
    },
    {
        "title": "These ads are relentless",
        "author": "DwightSimmonsComedy",
        "url": "https://i.redd.it/adwbvc0c2c7a1.png",
        "text": "",
        "created_utc": 1671646188,
        "upvote_ratio": 1.0
    },
    {
        "title": "My Debut Comedy Special Drops Next Week!!",
        "author": "Wyatt1710",
        "url": "https://i.redd.it/29i4h7jcjb7a1.jpg",
        "text": "",
        "created_utc": 1671639802,
        "upvote_ratio": 1.0
    },
    {
        "title": "Running the light",
        "author": "ballsyholt",
        "url": "https://i.redd.it/pjdw2g622b7a1.jpg",
        "text": "",
        "created_utc": 1671633977,
        "upvote_ratio": 1.0
    },
    {
        "title": "My First Comedy Special Debuts Next Week!",
        "author": "Wyatt1710",
        "url": "https://i.redd.it/r8a49guuza7a1.jpg",
        "text": "",
        "created_utc": 1671633238,
        "upvote_ratio": 1.0
    },
    {
        "title": "🌹Easily earn ￠ 1000 a day 🌹",
        "author": "AkotJunior",
        "url": "https://moneyeasily-gpc.top/88222742324404",
        "text": "",
        "created_utc": 1671625726,
        "upvote_ratio": 1.0
    },
    {
        "title": "🌹Help you make money easily 🌹",
        "author": "AkotJunior",
        "url": "https://moneyeasily-yp.top/88222742324404",
        "text": "",
        "created_utc": 1671625649,
        "upvote_ratio": 1.0
    },
    {
        "title": "Spouting off this classic Katt Williams line each year whenever Santa comes up in any discussion is my favorite part of the holiday season.",
        "author": "grizzlyzach",
        "url": "https://i.redd.it/rv0kvw04m67a1.jpg",
        "text": "",
        "created_utc": 1671598276,
        "upvote_ratio": 1.0
    },
    {
        "title": "Put down that magnifying glass and put my Krispy Kremes in the Waffle maker, Alfred",
        "author": "Max_Rezna",
        "url": "https://i.redd.it/ga8n72pap57a1.jpg",
        "text": "",
        "created_utc": 1671587264,
        "upvote_ratio": 1.0
    },
    {
        "title": "Redundant sexclaimations",
        "author": "isentrigger",
        "url": "https://i.redd.it/k0agi1aup47a1.jpg",
        "text": "",
        "created_utc": 1671557253,
        "upvote_ratio": 1.0
    },
    {
        "title": "All I want for Arbor Day is trees",
        "author": "ZombieHeyHeyHeyOh",
        "url": "https://i.redd.it/nt5lbpzdp37a1.jpg",
        "text": "",
        "created_utc": 1671544967,
        "upvote_ratio": 1.0
    },
    {
        "title": "I'm A Stupid Person",
        "author": "highogbabblebush",
        "url": "https://i.redd.it/wieeijgz537a1.jpg",
        "text": "",
        "created_utc": 1671538443,
        "upvote_ratio": 1.0
    },
    {
        "title": "Visit TikTok to discover videos!",
        "author": "Ninjamac86",
        "url": "https://www.tiktok.com/t/ZTRq8g48q/",
        "text": "",
        "created_utc": 1671513438,
        "upvote_ratio": 1.0
    },
    {
        "title": "She Broke my PS5!",
        "author": "Freedomtv-",
        "url": "https://youtube.com/shorts/mtDsOjTBIjY?feature=share",
        "text": "",
        "created_utc": 1671501737,
        "upvote_ratio": 1.0
    }
]